dice_roller/__init__.py
dice_roller/callback.py
dice_roller/compare.py
dice_roller/core.py
dice_roller/explode.py
dice_roller/math.py
dice_roller/misc.py
dice_roller/random.py
dice_roller/reroll.py
dice_roller/transformations.py
pydiceroll-0.4.2.dist-info/LICENSE.md
pydiceroll-0.4.2.dist-info/METADATA
pydiceroll-0.4.2.dist-info/WHEEL
pydiceroll-0.4.2.dist-info/top_level.txt
pydiceroll-0.4.2.dist-info/RECORD
