Metadata-Version: 2.1
Name: pydiceroll
Version: 0.4.2
Summary: Python tool for rolling a lot of dice
Author-email: Aleksei Zakharov <dokzlo13@gmail.com>
License: MIT
Project-URL: Homepage, https://github.com/dokzlo13/dice_roller
Project-URL: Repository, https://github.com/dokzlo13/dice_roller
Keywords: dice,simulation,probability,gaming,numpy
Classifier: Programming Language :: Python :: 3
Classifier: Programming Language :: Python :: 3.11
Classifier: License :: OSI Approved :: MIT License
Classifier: Intended Audience :: Developers
Classifier: Topic :: Games/Entertainment
Classifier: Topic :: Scientific/Engineering :: Mathematics
Classifier: Development Status :: 3 - Alpha
Requires-Python: >=3.11
License-File: LICENSE.md
Requires-Dist: numpy>=2.1.0
Requires-Dist: dyce>=0.6.2
